errornumbers/__init__.py
errornumbers/errornumbers.py
errornumbers-0.10.1.dist-info/WHEEL
errornumbers-0.10.1.dist-info/METADATA
errornumbers-0.10.1.dist-info/RECORD
