Metadata-Version: 2.1
Name: errornumbers
Version: 0.10.1
Summary: Classes and functions for handling with numbers with errors
Home-page: https://github.com/aap007freak/errornumbers
Author: Anton Leagre
Requires-Python: >=3.9,<4.0
Classifier: Programming Language :: Python :: 3
Classifier: Programming Language :: Python :: 3.9
Project-URL: Repository, https://github.com/aap007freak/errornumbers
